fast_trees/__init__.py
fast_trees/_nbdev.py
fast_trees/core.py
fast_trees/queries.py
fast_trees-0.0.3.dist-info/LICENSE
fast_trees-0.0.3.dist-info/METADATA
fast_trees-0.0.3.dist-info/WHEEL
fast_trees-0.0.3.dist-info/entry_points.txt
fast_trees-0.0.3.dist-info/top_level.txt
fast_trees-0.0.3.dist-info/RECORD
