Metadata-Version: 2.1
Name: fast-trees
Version: 0.0.3
Summary: Cute little python module that sits atop the tree-sitter library to provide an easier to use and cleaner interface for interacting with source code.
Home-page: https://github.com/ncoop57/fast_trees/tree/main/
Author: Nathan Cooper
Author-email: nathanallencooper@gmail.com
License: Apache Software License 2.0
Keywords: tree-sitter source code parser
Platform: UNKNOWN
Classifier: Development Status :: 3 - Alpha
Classifier: Intended Audience :: Developers
Classifier: License :: OSI Approved :: Apache Software License
Classifier: Natural Language :: English
Classifier: Programming Language :: Python :: 3.6
Classifier: Programming Language :: Python :: 3.7
Classifier: Programming Language :: Python :: 3.8
Requires-Python: >=3.6
Requires-Dist: GitPython (==3.1.11)
Requires-Dist: tree-sitter (==0.2.0)
